pixerise-0.12.2.dist-info/METADATA
pixerise-0.12.2.dist-info/WHEEL
pixerise-0.12.2.dist-info/entry_points.txt
pixerise-0.12.2.dist-info/licenses/LICENSE
pixerise/README.md
pixerise/kernel/clipping_mod.py
pixerise/kernel/culling_mod.py
pixerise/kernel/rasterizing_mod.py
pixerise/kernel/raycasting_mod.py
pixerise/kernel/rendering_mod.py
pixerise/kernel/shading_mod.py
pixerise/kernel/transforming_mod.py
pixerise/pixerise.py
pixerise/scene.py
pixerise-0.12.2.dist-info/RECORD
