Metadata-Version: 2.1
Name: pixerise
Version: 0.12.2
Summary: A high-performance 3D software renderer implemented in Python, optimized with NumPy and Numba JIT compilation.
Author-Email: Enrico Stara <enrico.stara@gmail.com>
License: MIT
Requires-Python: <3.13,>=3.10
Requires-Dist: numpy>=2.0.0
Requires-Dist: numba>=0.60.0
Requires-Dist: scipy>=1.14.1
